{"Name":"tb_raw_clientes", "StorageDescriptor":{ 
    "Columns":[
        { "Name":"id", "Type":"int" }, 
        { "Name":"nome", "Type":"string" }, 
        { "Name":"data_nasc", "Type":"date" }, 
        { "Name":"cpf", "Type":"string" }, 
        { "Name":"email", "Type":"string" }
    ], 
    "Location":"s3://COLE_O_NOME_DO_SEU_BUCKET_AQUI/raw/ecommerce/clientes/", 
    "InputFormat":"org.apache.hadoop.mapred.TextInputFormat",
    "SerdeInfo":{ 
        "SerializationLibrary":"org.apache.hadoop.hive.serde2.lazy.LazySimpleSerDe", 
        "Parameters":{ 
            "field.delim":";"
        } 
    }
    },
    "Parameters":{ 
        "classification":"csv", 
        "compressionType":"gzip", 
        "delimiter":";", 
        "typeOfData":"file",
        "skip.header.line.count":"1"
        }
}